{
	"database":
	{
		"driver": "sqlite",
		"host": "",
		"user": "",
		"pass": "",
		"name": "protected/data/test.db",
		"prefix": "lh_"
	},

	"url_router":
	{
		"default_controller": "site",
		"routes":
		[
			{
				"route": "index",
				"controller": "site"
			},
			{
				"route": "user",
				"controller": "view"
			},
			{
				"route": "user/:user_id",
				"controller": "view"
			}
		]
	},

	"themes":
	{
		"base": "protected/template"
	},

	"language": "en-US",

	"debug": false,
	"debug_lang": false
}
